email_processor/README.md
email_processor/__init__.py
email_processor/__main__.py
email_processor/__version__.py
email_processor/config.yaml.example
email_processor/exit_codes.py
email_processor/cli/__init__.py
email_processor/cli/args.py
email_processor/cli/ui.py
email_processor/cli/commands/__init__.py
email_processor/cli/commands/config.py
email_processor/cli/commands/imap.py
email_processor/cli/commands/passwords.py
email_processor/cli/commands/smtp.py
email_processor/cli/commands/status.py
email_processor/config/__init__.py
email_processor/config/constants.py
email_processor/config/loader.py
email_processor/imap/__init__.py
email_processor/imap/archive.py
email_processor/imap/attachments.py
email_processor/imap/auth.py
email_processor/imap/client.py
email_processor/imap/fetcher.py
email_processor/imap/filters.py
email_processor/imap/mock_client.py
email_processor/logging/__init__.py
email_processor/logging/formatters.py
email_processor/logging/setup.py
email_processor/security/__init__.py
email_processor/security/encryption.py
email_processor/security/fingerprint.py
email_processor/security/key_generator.py
email_processor/smtp/__init__.py
email_processor/smtp/client.py
email_processor/smtp/config.py
email_processor/smtp/sender.py
email_processor/storage/__init__.py
email_processor/storage/file_manager.py
email_processor/storage/sent_files_storage.py
email_processor/storage/uid_storage.py
email_processor/utils/__init__.py
email_processor/utils/context.py
email_processor/utils/disk_utils.py
email_processor/utils/email_utils.py
email_processor/utils/folder_resolver.py
email_processor/utils/path_utils.py
email_processor/utils/redact.py
email_processor-8.0.7.dist-info/licenses/LICENSE
tests/__init__.py
tests/conftest.py
tests/run_all_tests.py
tests/test_cli_integration.py
tests/test_full_cycle_integration.py
tests/test_integration.py
tests/test_security_integration.py
tests/test_smtp_integration.py
tests/benchmark/__init__.py
tests/benchmark/test_performance.py
tests/unit/__init__.py
tests/unit/conftest.py
email_processor-8.0.7.dist-info/METADATA
email_processor-8.0.7.dist-info/WHEEL
email_processor-8.0.7.dist-info/entry_points.txt
email_processor-8.0.7.dist-info/top_level.txt
email_processor-8.0.7.dist-info/RECORD
