Metadata-Version: 2.4
Name: email-processor
Version: 8.0.7
Summary: Email attachment processor with IMAP and SMTP support
Author-email: Valerii Kholodilin <kholodilin.valerii@gmail.com>
License-Expression: MIT
Project-URL: Homepage, https://github.com/KHolodilin/python-email-automation-processor
Project-URL: Bug Reports, https://github.com/KHolodilin/python-email-automation-processor/issues
Project-URL: Source, https://github.com/KHolodilin/python-email-automation-processor
Project-URL: Documentation, https://github.com/KHolodilin/python-email-automation-processor#readme
Keywords: email,imap,smtp,attachment,processor,automation
Classifier: Development Status :: 4 - Beta
Classifier: Intended Audience :: Developers
Classifier: Operating System :: OS Independent
Classifier: Programming Language :: Python :: 3
Classifier: Programming Language :: Python :: 3.9
Classifier: Programming Language :: Python :: 3.10
Classifier: Programming Language :: Python :: 3.11
Classifier: Programming Language :: Python :: 3.12
Classifier: Topic :: Communications :: Email
Classifier: Topic :: Software Development :: Libraries :: Python Modules
Classifier: Topic :: Utilities
Requires-Python: >=3.9
License-File: LICENSE
Requires-Dist: pyyaml>=6.0
Requires-Dist: keyring>=24.0
Requires-Dist: structlog>=24.0.0
Requires-Dist: tqdm>=4.66.0
Requires-Dist: cryptography>=40.0.0
Provides-Extra: dev
Requires-Dist: pytest>=7.0.0; extra == "dev"
Requires-Dist: pytest-cov>=4.0.0; extra == "dev"
Requires-Dist: ruff>=0.1.0; extra == "dev"
Requires-Dist: black>=23.0.0; extra == "dev"
Requires-Dist: mypy>=1.0.0; extra == "dev"
Requires-Dist: types-PyYAML>=6.0.0; extra == "dev"
Dynamic: license-file
